{
  "main": {
    "id": "110e0325e0b6021c",
    "type": "split",
    "children": [
      {
        "id": "4a82cf7e5f4d09b8",
        "type": "tabs",
        "children": [
          {
            "id": "0a72af4d83612cab",
            "type": "leaf",
            "state": {
              "type": "markdown",
              "state": {
                "file": "Federation/Federation Impact Report_ Chrystallum Data Targets.md",
                "mode": "preview",
                "source": false
              },
              "icon": "lucide-file",
              "title": "Federation Impact Report_ Chrystallum Data Targets"
            }
          },
          {
            "id": "bfb0410ff00f38aa",
            "type": "leaf",
            "state": {
              "type": "markdown",
              "state": {
                "file": "Geographic/LOGICAL_MODEL.md",
                "mode": "source",
                "source": false
              },
              "icon": "lucide-file",
              "title": "LOGICAL_MODEL"
            }
          }
        ],
        "currentTab": 1
      }
    ],
    "direction": "vertical"
  },
  "left": {
    "id": "7be90003d56b0ca1",
    "type": "split",
    "children": [
      {
        "id": "498ef5e5e96d15c1",
        "type": "tabs",
        "children": [
          {
            "id": "3e99074504874fc7",
            "type": "leaf",
            "state": {
              "type": "file-explorer",
              "state": {
                "sortOrder": "alphabetical",
                "autoReveal": false
              },
              "icon": "lucide-folder-closed",
              "title": "Files"
            }
          },
          {
            "id": "1a3a7ec2680b0011",
            "type": "leaf",
            "state": {
              "type": "search",
              "state": {
                "query": "",
                "matchingCase": false,
                "explainSearch": false,
                "collapseAll": false,
                "extraContext": false,
                "sortOrder": "alphabetical"
              },
              "icon": "lucide-search",
              "title": "Search"
            }
          },
          {
            "id": "e18c1944956e8f30",
            "type": "leaf",
            "state": {
              "type": "bookmarks",
              "state": {},
              "icon": "lucide-bookmark",
              "title": "Bookmarks"
            }
          }
        ]
      }
    ],
    "direction": "horizontal",
    "width": 432.5
  },
  "right": {
    "id": "823b7d0fcf317f53",
    "type": "split",
    "children": [
      {
        "id": "de72b0ed2c960c23",
        "type": "tabs",
        "children": [
          {
            "id": "cd0c93e4384c53c0",
            "type": "leaf",
            "state": {
              "type": "backlink",
              "state": {
                "file": "bdd periodo.md",
                "collapseAll": false,
                "extraContext": false,
                "sortOrder": "alphabetical",
                "showSearch": false,
                "searchQuery": "",
                "backlinkCollapsed": false,
                "unlinkedCollapsed": true
              },
              "icon": "links-coming-in",
              "title": "Backlinks for bdd periodo"
            }
          },
          {
            "id": "4be79e56d3583d7b",
            "type": "leaf",
            "state": {
              "type": "outgoing-link",
              "state": {
                "file": "bdd periodo.md",
                "linksCollapsed": false,
                "unlinkedCollapsed": true
              },
              "icon": "links-going-out",
              "title": "Outgoing links from bdd periodo"
            }
          },
          {
            "id": "dd2a81613d476886",
            "type": "leaf",
            "state": {
              "type": "tag",
              "state": {
                "sortOrder": "frequency",
                "useHierarchy": true,
                "showSearch": false,
                "searchQuery": ""
              },
              "icon": "lucide-tags",
              "title": "Tags"
            }
          },
          {
            "id": "a72b624c4312732a",
            "type": "leaf",
            "state": {
              "type": "all-properties",
              "state": {
                "sortOrder": "frequency",
                "showSearch": false,
                "searchQuery": ""
              },
              "icon": "lucide-archive",
              "title": "All properties"
            }
          },
          {
            "id": "ac52bea06c97a48b",
            "type": "leaf",
            "state": {
              "type": "outline",
              "state": {
                "file": "bdd periodo.md",
                "followCursor": false,
                "showSearch": false,
                "searchQuery": ""
              },
              "icon": "lucide-list",
              "title": "Outline of bdd periodo"
            }
          }
        ]
      }
    ],
    "direction": "horizontal",
    "width": 300,
    "collapsed": true
  },
  "left-ribbon": {
    "hiddenItems": {
      "switcher:Open quick switcher": false,
      "graph:Open graph view": false,
      "canvas:Create new canvas": false,
      "daily-notes:Open today's daily note": false,
      "templates:Insert template": false,
      "command-palette:Open command palette": false,
      "bases:Create new base": false
    }
  },
  "active": "bfb0410ff00f38aa",
  "lastOpenFiles": [
    "docs/DATA_DICTIONARY.md",
    "Geographic/README.md",
    "Geographic/LOGICAL_MODEL.md",
    "docs/PLACE_LOGICAL_MODEL.md",
    "viewer/node_modules/@babel/parser/CHANGELOG.md",
    "viewer/node_modules/vite/index.cjs",
    "viewer/node_modules/vite/client.d.ts",
    "viewer/node_modules/vite/README.md",
    "viewer/node_modules/vite/LICENSE.md",
    "viewer/node_modules/update-browserslist-db/index.js",
    "viewer/node_modules/update-browserslist-db/index.d.ts",
    "viewer/node_modules/debug/LICENSE",
    "viewer/node_modules/update-browserslist-db/cli.js",
    "viewer/node_modules/convert-source-map/package.json",
    "viewer/node_modules/update-browserslist-db/check-npm-version.js",
    "viewer/node_modules/convert-source-map/index.js",
    "viewer/node_modules/update-browserslist-db/README.md",
    "docs/D034_MCP_PHASE2_SPEC.md",
    "Key Files/ARCHITECTURE_CORE.md",
    "03-03-26 Chrystallum Consolidated.md",
    "output/census.json",
    "docs/BLOOM_SHOW_EDGE_LABELS.md",
    "docs/AGENT_HANDOFF_2026-03-06.md",
    "docs/BIO_CENTURY_PRECISION_DPRR_CROSSCHECK.md",
    "docs/POSITION_ACTIVE_IN_YEAR_GAP.md",
    "viewer/node_modules/scheduler/README.md",
    "viewer/node_modules/baseline-browser-mapping/README.md",
    "viewer/node_modules/react-refresh/README.md",
    "viewer/node_modules/js-tokens/CHANGELOG.md",
    "viewer/node_modules/gensync/README.md",
    "docs/BIO_BACKLINK_REVERSAL_PLAN.md",
    "viewer/node_modules/@vitejs/plugin-react/README.md",
    "viewer/node_modules/@types/babel__traverse/README.md",
    "viewer/node_modules/@jridgewell/sourcemap-codec/README.md",
    "viewer/node_modules/@jridgewell/resolve-uri/README.md",
    "viewer/node_modules/@jridgewell/remapping/README.md",
    "Chrystallum Query Executor - Capabilities Overview_files/80ad787d-3879-452c-8291-67b9df21e81b.png",
    "Chrystallum Query Executor - Capabilities Overview_files/51440a0b-ecb6-4bea-bd08-af795e05a2f0.png",
    "Chrystallum Query Executor - Capabilities Overview_files/0c016ee8-0565-4df6-94ca-81418d52d70b.png",
    "Chrystallum Query Executor - Capabilities Overview_files/9d8cd6fe-b5f3-4383-b496-f5305415d4cc.png",
    "Chrystallum Query Executor - Capabilities Overview_files/visualisation.png",
    "Chrystallum Query Executor - Capabilities Overview_files/8820e88c-fb82-48ee-a64c-18567c07b3fd.png",
    "Chrystallum Query Executor - Capabilities Overview_files/0f7a5070-b75b-4275-9f5f-d7df3f8f9175.png",
    "Chrystallum Query Executor - Capabilities Overview_files/d891802d-3af0-49bb-9614-6b2c521b6c8e.png",
    "visualisation.png",
    "Key Files/Diagrams/cypher_patterns.png"
  ]
}