[
  {
    "id": "E11-143",
    "code": "E11-143",
    "prefix": "E",
    "start": 11.0,
    "end": 143.0,
    "label": "America",
    "note": null,
    "primary_parent": null,
    "secondary_parents": [],
    "children": [
      "E11-29",
      "E31-49.2",
      "E51-73",
      "E75-99",
      "E101-135",
      "E141-143"
    ]
  },
  {
    "id": "E11-29",
    "code": "E11-29",
    "prefix": "E",
    "start": 11.0,
    "end": 29.0,
    "label": "General",
    "note": null,
    "primary_parent": "E11-143",
    "secondary_parents": [],
    "children": [
      "E29"
    ]
  },
  {
    "id": "E29",
    "code": "E29",
    "prefix": "E",
    "start": 29.0,
    "end": 29.0,
    "label": "Elements in the population",
    "note": null,
    "primary_parent": "E11-29",
    "secondary_parents": [],
    "children": []
  },
  {
    "id": "E31-49.2",
    "code": "E31-49.2",
    "prefix": "E",
    "start": 31.0,
    "end": 49.2,
    "label": "North America",
    "note": null,
    "primary_parent": "E11-143",
    "secondary_parents": [],
    "children": []
  },
  {
    "id": "E51-73",
    "code": "E51-73",
    "prefix": "E",
    "start": 51.0,
    "end": 73.0,
    "label": "Pre-Columbian America.  The Indians",
    "note": null,
    "primary_parent": "E11-143",
    "secondary_parents": [],
    "children": []
  },
  {
    "id": "E75-99",
    "code": "E75-99",
    "prefix": "E",
    "start": 75.0,
    "end": 99.0,
    "label": "Indians of North America",
    "note": null,
    "primary_parent": "E11-143",
    "secondary_parents": [],
    "children": [
      "E81-83",
      "E99"
    ]
  },
  {
    "id": "E81-83",
    "code": "E81-83",
    "prefix": "E",
    "start": 81.0,
    "end": 83.0,
    "label": "Indian wars",
    "note": null,
    "primary_parent": "E75-99",
    "secondary_parents": [],
    "children": []
  },
  {
    "id": "E99",
    "code": "E99",
    "prefix": "E",
    "start": 99.0,
    "end": 99.0,
    "label": "Indian tribes and cultures",
    "note": null,
    "primary_parent": "E75-99",
    "secondary_parents": [],
    "children": []
  },
  {
    "id": "E101-135",
    "code": "E101-135",
    "prefix": "E",
    "start": 101.0,
    "end": 135.0,
    "label": "Discovery of America and early explorations",
    "note": null,
    "primary_parent": "E11-143",
    "secondary_parents": [],
    "children": [
      "E103-110",
      "E111-120",
      "E121-135"
    ]
  },
  {
    "id": "E103-110",
    "code": "E103-110",
    "prefix": "E",
    "start": 103.0,
    "end": 110.0,
    "label": "Pre-Columbian period",
    "note": null,
    "primary_parent": "E101-135",
    "secondary_parents": [],
    "children": []
  },
  {
    "id": "E111-120",
    "code": "E111-120",
    "prefix": "E",
    "start": 111.0,
    "end": 120.0,
    "label": "Columbus",
    "note": null,
    "primary_parent": "E101-135",
    "secondary_parents": [],
    "children": []
  },
  {
    "id": "E121-135",
    "code": "E121-135",
    "prefix": "E",
    "start": 121.0,
    "end": 135.0,
    "label": "Post-Columbian period.  El Dorado",
    "note": null,
    "primary_parent": "E101-135",
    "secondary_parents": [],
    "children": []
  },
  {
    "id": "E141-143",
    "code": "E141-143",
    "prefix": "E",
    "start": 141.0,
    "end": 143.0,
    "label": "Descriptive accounts of America.  Earliest to 1810",
    "note": null,
    "primary_parent": "E11-143",
    "secondary_parents": [],
    "children": []
  },
  {
    "id": "E151-889",
    "code": "E151-889",
    "prefix": "E",
    "start": 151.0,
    "end": 889.0,
    "label": "United States",
    "note": null,
    "primary_parent": null,
    "secondary_parents": [],
    "children": [
      "E151-169.12",
      "E171-183.9",
      "E184.5-185.98",
      "E186-189",
      "E191-199",
      "E300-453",
      "E456-655",
      "E660-738",
      "E740-837.7",
      "E838-889"
    ]
  },
  {
    "id": "E151-169.12",
    "code": "E151-169.12",
    "prefix": "E",
    "start": 151.0,
    "end": 169.12,
    "label": "General",
    "note": null,
    "primary_parent": "E151-889",
    "secondary_parents": [],
    "children": []
  },
  {
    "id": "E171-183.9",
    "code": "E171-183.9",
    "prefix": "E",
    "start": 171.0,
    "end": 183.9,
    "label": "History",
    "note": null,
    "primary_parent": "E151-889",
    "secondary_parents": [],
    "children": [
      "E171-180",
      "E181",
      "E182",
      "E183-183.3",
      "E183.7-183.9"
    ]
  },
  {
    "id": "E171-180",
    "code": "E171-180",
    "prefix": "E",
    "start": 171.0,
    "end": 180.0,
    "label": "General",
    "note": null,
    "primary_parent": "E171-183.9",
    "secondary_parents": [],
    "children": [
      "E173",
      "E175-175.7",
      "E176-176.8",
      "E179.5"
    ]
  },
  {
    "id": "E173",
    "code": "E173",
    "prefix": "E",
    "start": 173.0,
    "end": 173.0,
    "label": "Sources and documents",
    "note": null,
    "primary_parent": "E171-180",
    "secondary_parents": [],
    "children": []
  },
  {
    "id": "E175-175.7",
    "code": "E175-175.7",
    "prefix": "E",
    "start": 175.0,
    "end": 175.7,
    "label": "Historiography",
    "note": null,
    "primary_parent": "E171-180",
    "secondary_parents": [],
    "children": []
  },
  {
    "id": "E176-176.8",
    "code": "E176-176.8",
    "prefix": "E",
    "start": 176.0,
    "end": 176.8,
    "label": "Biography",
    "note": null,
    "primary_parent": "E171-180",
    "secondary_parents": [],
    "children": []
  },
  {
    "id": "E179.5",
    "code": "E179.5",
    "prefix": "E",
    "start": 179.5,
    "end": 179.5,
    "label": "Historical geography",
    "note": null,
    "primary_parent": "E171-180",
    "secondary_parents": [],
    "children": []
  },
  {
    "id": "E181",
    "code": "E181",
    "prefix": "E",
    "start": 181.0,
    "end": 181.0,
    "label": "Military history",
    "note": null,
    "primary_parent": "E171-183.9",
    "secondary_parents": [],
    "children": []
  },
  {
    "id": "E182",
    "code": "E182",
    "prefix": "E",
    "start": 182.0,
    "end": 182.0,
    "label": "Naval history",
    "note": null,
    "primary_parent": "E171-183.9",
    "secondary_parents": [],
    "children": []
  },
  {
    "id": "E183-183.3",
    "code": "E183-183.3",
    "prefix": "E",
    "start": 183.0,
    "end": 183.3,
    "label": "Political history",
    "note": null,
    "primary_parent": "E171-183.9",
    "secondary_parents": [],
    "children": []
  },
  {
    "id": "E183.7-183.9",
    "code": "E183.7-183.9",
    "prefix": "E",
    "start": 183.7,
    "end": 183.9,
    "label": "Diplomatic history.  Foreign and general relations.",
    "note": null,
    "primary_parent": "E171-183.9",
    "secondary_parents": [],
    "children": [
      "E183.8"
    ]
  },
  {
    "id": "E183.8",
    "code": "E183.8",
    "prefix": "E",
    "start": 183.8,
    "end": 183.8,
    "label": "Relations with individual countries E184-185.98                               Elements in the population",
    "note": null,
    "primary_parent": "E183.7-183.9",
    "secondary_parents": [],
    "children": []
  },
  {
    "id": "E184.5-185.98",
    "code": "E184.5-185.98",
    "prefix": "E",
    "start": 184.5,
    "end": 185.98,
    "label": "Afro-Americans",
    "note": null,
    "primary_parent": "E151-889",
    "secondary_parents": [],
    "children": [
      "E185.2-185.89",
      "E185.96-185.98"
    ]
  },
  {
    "id": "E185.2-185.89",
    "code": "E185.2-185.89",
    "prefix": "E",
    "start": 185.2,
    "end": 185.89,
    "label": "Status and development since emancipation",
    "note": null,
    "primary_parent": "E184.5-185.98",
    "secondary_parents": [],
    "children": []
  },
  {
    "id": "E185.96-185.98",
    "code": "E185.96-185.98",
    "prefix": "E",
    "start": 185.96,
    "end": 185.98,
    "label": "Biography.  Genealogy E186-199                                    Colonial history (1607-1775)",
    "note": null,
    "primary_parent": "E184.5-185.98",
    "secondary_parents": [],
    "children": []
  },
  {
    "id": "E186-189",
    "code": "E186-189",
    "prefix": "E",
    "start": 186.0,
    "end": 189.0,
    "label": "General",
    "note": null,
    "primary_parent": "E151-889",
    "secondary_parents": [],
    "children": []
  },
  {
    "id": "E191-199",
    "code": "E191-199",
    "prefix": "E",
    "start": 191.0,
    "end": 199.0,
    "label": "By period",
    "note": null,
    "primary_parent": "E151-889",
    "secondary_parents": [],
    "children": [
      "E191",
      "E195-199"
    ]
  },
  {
    "id": "E191",
    "code": "E191",
    "prefix": "E",
    "start": 191.0,
    "end": 191.0,
    "label": "1607-1689",
    "note": null,
    "primary_parent": "E191-199",
    "secondary_parents": [],
    "children": []
  },
  {
    "id": "E195-199",
    "code": "E195-199",
    "prefix": "E",
    "start": 195.0,
    "end": 199.0,
    "label": "1689-1775",
    "note": null,
    "primary_parent": "E191-199",
    "secondary_parents": [],
    "children": [
      "E196",
      "E197",
      "E198",
      "E199"
    ]
  },
  {
    "id": "E196",
    "code": "E196",
    "prefix": "E",
    "start": 196.0,
    "end": 196.0,
    "label": "King William's War, 1689-1697",
    "note": null,
    "primary_parent": "E195-199",
    "secondary_parents": [],
    "children": []
  },
  {
    "id": "E197",
    "code": "E197",
    "prefix": "E",
    "start": 197.0,
    "end": 197.0,
    "label": "Queen Anne's War, 1702-1713",
    "note": null,
    "primary_parent": "E195-199",
    "secondary_parents": [],
    "children": []
  },
  {
    "id": "E198",
    "code": "E198",
    "prefix": "E",
    "start": 198.0,
    "end": 198.0,
    "label": "King George's War, 1744-1748",
    "note": null,
    "primary_parent": "E195-199",
    "secondary_parents": [],
    "children": []
  },
  {
    "id": "E199",
    "code": "E199",
    "prefix": "E",
    "start": 199.0,
    "end": 199.0,
    "label": "French and Indian War, 1755-1763 E201-298                                    The Revolution, 1775-1783",
    "note": null,
    "primary_parent": "E195-199",
    "secondary_parents": [],
    "children": []
  },
  {
    "id": "E300-453",
    "code": "E300-453",
    "prefix": "E",
    "start": 300.0,
    "end": 453.0,
    "label": "Revolution to the Civil War, 1775/1783-1861",
    "note": null,
    "primary_parent": "E151-889",
    "secondary_parents": [],
    "children": [
      "E300-302.6",
      "E303-440.5",
      "E441-453"
    ]
  },
  {
    "id": "E300-302.6",
    "code": "E300-302.6",
    "prefix": "E",
    "start": 300.0,
    "end": 302.6,
    "label": "General",
    "note": null,
    "primary_parent": "E300-453",
    "secondary_parents": [],
    "children": [
      "E302",
      "E302.1",
      "E302.5-302.6"
    ]
  },
  {
    "id": "E302",
    "code": "E302",
    "prefix": "E",
    "start": 302.0,
    "end": 302.0,
    "label": "Collected works of American statesmen",
    "note": null,
    "primary_parent": "E300-302.6",
    "secondary_parents": [],
    "children": []
  },
  {
    "id": "E302.1",
    "code": "E302.1",
    "prefix": "E",
    "start": 302.1,
    "end": 302.1,
    "label": "Political history",
    "note": null,
    "primary_parent": "E300-302.6",
    "secondary_parents": [],
    "children": []
  },
  {
    "id": "E302.5-302.6",
    "code": "E302.5-302.6",
    "prefix": "E",
    "start": 302.5,
    "end": 302.6,
    "label": "Biography (Late eighteenth century)",
    "note": null,
    "primary_parent": "E300-302.6",
    "secondary_parents": [],
    "children": []
  },
  {
    "id": "E303-440.5",
    "code": "E303-440.5",
    "prefix": "E",
    "start": 303.0,
    "end": 440.5,
    "label": "By period",
    "note": null,
    "primary_parent": "E300-453",
    "secondary_parents": [],
    "children": [
      "E303-309",
      "E310-337",
      "E337.8-400",
      "E408",
      "E415.6-440.5"
    ]
  },
  {
    "id": "E303-309",
    "code": "E303-309",
    "prefix": "E",
    "start": 303.0,
    "end": 309.0,
    "label": "1775-1789.  The Confederation, 1783-1789",
    "note": null,
    "primary_parent": "E303-440.5",
    "secondary_parents": [],
    "children": []
  },
  {
    "id": "E310-337",
    "code": "E310-337",
    "prefix": "E",
    "start": 310.0,
    "end": 337.0,
    "label": "1789-1809.  Constitutional period",
    "note": null,
    "primary_parent": "E303-440.5",
    "secondary_parents": [],
    "children": [
      "E310.7",
      "E311-320",
      "E321-330",
      "E331-337"
    ]
  },
  {
    "id": "E310.7",
    "code": "E310.7",
    "prefix": "E",
    "start": 310.7,
    "end": 310.7,
    "label": "Diplomatic history.  Foreign and general relations",
    "note": null,
    "primary_parent": "E310-337",
    "secondary_parents": [],
    "children": []
  },
  {
    "id": "E311-320",
    "code": "E311-320",
    "prefix": "E",
    "start": 311.0,
    "end": 320.0,
    "label": "Washington's administrations, 1789-1797",
    "note": null,
    "primary_parent": "E310-337",
    "secondary_parents": [],
    "children": []
  },
  {
    "id": "E321-330",
    "code": "E321-330",
    "prefix": "E",
    "start": 321.0,
    "end": 330.0,
    "label": "John Adams' administration, 1797-1801",
    "note": null,
    "primary_parent": "E310-337",
    "secondary_parents": [],
    "children": [
      "E323"
    ]
  },
  {
    "id": "E323",
    "code": "E323",
    "prefix": "E",
    "start": 323.0,
    "end": 323.0,
    "label": "Troubles with France, 1796-1800",
    "note": null,
    "primary_parent": "E321-330",
    "secondary_parents": [],
    "children": []
  },
  {
    "id": "E331-337",
    "code": "E331-337",
    "prefix": "E",
    "start": 331.0,
    "end": 337.0,
    "label": "Jefferson's administrations, 1801-1809",
    "note": null,
    "primary_parent": "E310-337",
    "secondary_parents": [],
    "children": [
      "E333",
      "E335",
      "E336-336.5"
    ]
  },
  {
    "id": "E333",
    "code": "E333",
    "prefix": "E",
    "start": 333.0,
    "end": 333.0,
    "label": "Purchase of Louisiana, 1803",
    "note": null,
    "primary_parent": "E331-337",
    "secondary_parents": [],
    "children": []
  },
  {
    "id": "E335",
    "code": "E335",
    "prefix": "E",
    "start": 335.0,
    "end": 335.0,
    "label": "War with Tripoli, 1801-1805",
    "note": null,
    "primary_parent": "E331-337",
    "secondary_parents": [],
    "children": []
  },
  {
    "id": "E336-336.5",
    "code": "E336-336.5",
    "prefix": "E",
    "start": 336.0,
    "end": 336.5,
    "label": "Neutral trade and its restrictions, 1800-1810 E337.5                                               Nineteenth century (General)",
    "note": null,
    "primary_parent": "E331-337",
    "secondary_parents": [],
    "children": []
  },
  {
    "id": "E337.8-400",
    "code": "E337.8-400",
    "prefix": "E",
    "start": 337.8,
    "end": 400.0,
    "label": "Early nineteenth century, 1801/1809-1845",
    "note": null,
    "primary_parent": "E303-440.5",
    "secondary_parents": [],
    "children": [
      "E337.8-340",
      "E341-370",
      "E371-375",
      "E376-380",
      "E381-385",
      "E386-390",
      "E391-392",
      "E396-400"
    ]
  },
  {
    "id": "E337.8-340",
    "code": "E337.8-340",
    "prefix": "E",
    "start": 337.8,
    "end": 340.0,
    "label": "General",
    "note": null,
    "primary_parent": "E337.8-400",
    "secondary_parents": [],
    "children": [
      "E337.8",
      "E339-340"
    ]
  },
  {
    "id": "E337.8",
    "code": "E337.8",
    "prefix": "E",
    "start": 337.8,
    "end": 337.8,
    "label": "Collected works of American statesmen",
    "note": null,
    "primary_parent": "E337.8-340",
    "secondary_parents": [],
    "children": []
  },
  {
    "id": "E339-340",
    "code": "E339-340",
    "prefix": "E",
    "start": 339.0,
    "end": 340.0,
    "label": "Biography",
    "note": null,
    "primary_parent": "E337.8-340",
    "secondary_parents": [],
    "children": []
  },
  {
    "id": "E341-370",
    "code": "E341-370",
    "prefix": "E",
    "start": 341.0,
    "end": 370.0,
    "label": "Madison's administrations, 1809-1817",
    "note": null,
    "primary_parent": "E337.8-400",
    "secondary_parents": [],
    "children": [
      "E351.5-364.9",
      "E365"
    ]
  },
  {
    "id": "E351.5-364.9",
    "code": "E351.5-364.9",
    "prefix": "E",
    "start": 351.5,
    "end": 364.9,
    "label": "War of 1812",
    "note": null,
    "primary_parent": "E341-370",
    "secondary_parents": [],
    "children": []
  },
  {
    "id": "E365",
    "code": "E365",
    "prefix": "E",
    "start": 365.0,
    "end": 365.0,
    "label": "War with Algeria, 1815",
    "note": null,
    "primary_parent": "E341-370",
    "secondary_parents": [],
    "children": []
  },
  {
    "id": "E371-375",
    "code": "E371-375",
    "prefix": "E",
    "start": 371.0,
    "end": 375.0,
    "label": "Monroe's administrations, 1817-1825",
    "note": null,
    "primary_parent": "E337.8-400",
    "secondary_parents": [],
    "children": [
      "E373",
      "E374"
    ]
  },
  {
    "id": "E373",
    "code": "E373",
    "prefix": "E",
    "start": 373.0,
    "end": 373.0,
    "label": "Missouri Compromise, 1820",
    "note": null,
    "primary_parent": "E371-375",
    "secondary_parents": [],
    "children": []
  },
  {
    "id": "E374",
    "code": "E374",
    "prefix": "E",
    "start": 374.0,
    "end": 374.0,
    "label": "Diplomatic history.  Foreign relations",
    "note": null,
    "primary_parent": "E371-375",
    "secondary_parents": [],
    "children": []
  },
  {
    "id": "E376-380",
    "code": "E376-380",
    "prefix": "E",
    "start": 376.0,
    "end": 380.0,
    "label": "John Quincy Adams' administration, 1825-1829",
    "note": null,
    "primary_parent": "E337.8-400",
    "secondary_parents": [],
    "children": []
  },
  {
    "id": "E381-385",
    "code": "E381-385",
    "prefix": "E",
    "start": 381.0,
    "end": 385.0,
    "label": "Jackson's administrations, 1829-1837",
    "note": null,
    "primary_parent": "E337.8-400",
    "secondary_parents": [],
    "children": [
      "E384.3"
    ]
  },
  {
    "id": "E384.3",
    "code": "E384.3",
    "prefix": "E",
    "start": 384.3,
    "end": 384.3,
    "label": "Nullification",
    "note": null,
    "primary_parent": "E381-385",
    "secondary_parents": [],
    "children": []
  },
  {
    "id": "E386-390",
    "code": "E386-390",
    "prefix": "E",
    "start": 386.0,
    "end": 390.0,
    "label": "Van Buren's administration, 1837-1841",
    "note": null,
    "primary_parent": "E337.8-400",
    "secondary_parents": [],
    "children": []
  },
  {
    "id": "E391-392",
    "code": "E391-392",
    "prefix": "E",
    "start": 391.0,
    "end": 392.0,
    "label": "William H. Harrison's administration, March 4- April 4, 1841",
    "note": null,
    "primary_parent": "E337.8-400",
    "secondary_parents": [],
    "children": []
  },
  {
    "id": "E396-400",
    "code": "E396-400",
    "prefix": "E",
    "start": 396.0,
    "end": 400.0,
    "label": "Tyler's administration, April 4, 1841-1845",
    "note": null,
    "primary_parent": "E337.8-400",
    "secondary_parents": [],
    "children": [
      "E398"
    ]
  },
  {
    "id": "E398",
    "code": "E398",
    "prefix": "E",
    "start": 398.0,
    "end": 398.0,
    "label": "Northeastern boundary disputes, 1783-1845 E401-415.2                                        Mexican War, 1846-1848",
    "note": null,
    "primary_parent": "E396-400",
    "secondary_parents": [],
    "children": []
  },
  {
    "id": "E408",
    "code": "E408",
    "prefix": "E",
    "start": 408.0,
    "end": 408.0,
    "label": "Mexican cessions of 1848",
    "note": null,
    "primary_parent": "E303-440.5",
    "secondary_parents": [],
    "children": []
  },
  {
    "id": "E415.6-440.5",
    "code": "E415.6-440.5",
    "prefix": "E",
    "start": 415.6,
    "end": 440.5,
    "label": "Middle nineteenth century, 1845/1848-1861",
    "note": null,
    "primary_parent": "E303-440.5",
    "secondary_parents": [],
    "children": [
      "E415.6-415.9",
      "E416-420",
      "E421-423",
      "E426-430",
      "E431-435",
      "E436-440.5"
    ]
  },
  {
    "id": "E415.6-415.9",
    "code": "E415.6-415.9",
    "prefix": "E",
    "start": 415.6,
    "end": 415.9,
    "label": "General",
    "note": null,
    "primary_parent": "E415.6-440.5",
    "secondary_parents": [],
    "children": [
      "E415.6",
      "E415.8-415.9"
    ]
  },
  {
    "id": "E415.6",
    "code": "E415.6",
    "prefix": "E",
    "start": 415.6,
    "end": 415.6,
    "label": "Collected works of American statesmen",
    "note": null,
    "primary_parent": "E415.6-415.9",
    "secondary_parents": [],
    "children": []
  },
  {
    "id": "E415.8-415.9",
    "code": "E415.8-415.9",
    "prefix": "E",
    "start": 415.8,
    "end": 415.9,
    "label": "Biography",
    "note": null,
    "primary_parent": "E415.6-415.9",
    "secondary_parents": [],
    "children": []
  },
  {
    "id": "E416-420",
    "code": "E416-420",
    "prefix": "E",
    "start": 416.0,
    "end": 420.0,
    "label": "Polk's administration, 1845-1849",
    "note": null,
    "primary_parent": "E415.6-440.5",
    "secondary_parents": [],
    "children": []
  },
  {
    "id": "E421-423",
    "code": "E421-423",
    "prefix": "E",
    "start": 421.0,
    "end": 423.0,
    "label": "Taylor's administration, 1849-July 9, 1850",
    "note": null,
    "primary_parent": "E415.6-440.5",
    "secondary_parents": [],
    "children": [
      "E423"
    ]
  },
  {
    "id": "E423",
    "code": "E423",
    "prefix": "E",
    "start": 423.0,
    "end": 423.0,
    "label": "Slavery question, 1849-1853",
    "note": null,
    "primary_parent": "E421-423",
    "secondary_parents": [],
    "children": []
  },
  {
    "id": "E426-430",
    "code": "E426-430",
    "prefix": "E",
    "start": 426.0,
    "end": 430.0,
    "label": "Fillmore's administration, July 9, 1850-1853",
    "note": null,
    "primary_parent": "E415.6-440.5",
    "secondary_parents": [],
    "children": []
  },
  {
    "id": "E431-435",
    "code": "E431-435",
    "prefix": "E",
    "start": 431.0,
    "end": 435.0,
    "label": "Pierce's administration, 1853-1857",
    "note": null,
    "primary_parent": "E415.6-440.5",
    "secondary_parents": [],
    "children": [
      "E433"
    ]
  },
  {
    "id": "E433",
    "code": "E433",
    "prefix": "E",
    "start": 433.0,
    "end": 433.0,
    "label": "Slavery question, 1853-1857",
    "note": null,
    "primary_parent": "E431-435",
    "secondary_parents": [],
    "children": []
  },
  {
    "id": "E436-440.5",
    "code": "E436-440.5",
    "prefix": "E",
    "start": 436.0,
    "end": 440.5,
    "label": "Buchanan's administration, 1857-1861",
    "note": null,
    "primary_parent": "E415.6-440.5",
    "secondary_parents": [],
    "children": [
      "E438",
      "E440.5"
    ]
  },
  {
    "id": "E438",
    "code": "E438",
    "prefix": "E",
    "start": 438.0,
    "end": 438.0,
    "label": "Slavery question, 1857-1861",
    "note": null,
    "primary_parent": "E436-440.5",
    "secondary_parents": [],
    "children": []
  },
  {
    "id": "E440.5",
    "code": "E440.5",
    "prefix": "E",
    "start": 440.5,
    "end": 440.5,
    "label": "State of the country, November 1860- March 4, 1861",
    "note": null,
    "primary_parent": "E436-440.5",
    "secondary_parents": [],
    "children": []
  },
  {
    "id": "E441-453",
    "code": "E441-453",
    "prefix": "E",
    "start": 441.0,
    "end": 453.0,
    "label": "Slavery in the United States.  Antislavery movements",
    "note": null,
    "primary_parent": "E300-453",
    "secondary_parents": [],
    "children": []
  },
  {
    "id": "E456-655",
    "code": "E456-655",
    "prefix": "E",
    "start": 456.0,
    "end": 655.0,
    "label": "Civil War period, 1861-1865",
    "note": null,
    "primary_parent": "E151-889",
    "secondary_parents": [],
    "children": [
      "E456-459",
      "E461-655"
    ]
  },
  {
    "id": "E456-459",
    "code": "E456-459",
    "prefix": "E",
    "start": 456.0,
    "end": 459.0,
    "label": "Lincoln's administrations, 1861-April 15, 1865",
    "note": null,
    "primary_parent": "E456-655",
    "secondary_parents": [],
    "children": []
  },
  {
    "id": "E461-655",
    "code": "E461-655",
    "prefix": "E",
    "start": 461.0,
    "end": 655.0,
    "label": "The Civil War, 1861-1865",
    "note": null,
    "primary_parent": "E456-655",
    "secondary_parents": [],
    "children": [
      "E482-489",
      "E491-586",
      "E591-600"
    ]
  },
  {
    "id": "E482-489",
    "code": "E482-489",
    "prefix": "E",
    "start": 482.0,
    "end": 489.0,
    "label": "Confederate States of America",
    "note": null,
    "primary_parent": "E461-655",
    "secondary_parents": [],
    "children": []
  },
  {
    "id": "E491-586",
    "code": "E491-586",
    "prefix": "E",
    "start": 491.0,
    "end": 586.0,
    "label": "Armies.  Troops",
    "note": null,
    "primary_parent": "E461-655",
    "secondary_parents": [],
    "children": []
  },
  {
    "id": "E591-600",
    "code": "E591-600",
    "prefix": "E",
    "start": 591.0,
    "end": 600.0,
    "label": "Naval history",
    "note": null,
    "primary_parent": "E461-655",
    "secondary_parents": [],
    "children": []
  },
  {
    "id": "E660-738",
    "code": "E660-738",
    "prefix": "E",
    "start": 660.0,
    "end": 738.0,
    "label": "Late nineteenth century, 1865-1900",
    "note": null,
    "primary_parent": "E151-889",
    "secondary_parents": [],
    "children": [
      "E660-664",
      "E666-670",
      "E671-680",
      "E681-685",
      "E686-687.9",
      "E691-695",
      "E696-700",
      "E701-705",
      "E706-710",
      "E711-738"
    ]
  },
  {
    "id": "E660-664",
    "code": "E660-664",
    "prefix": "E",
    "start": 660.0,
    "end": 664.0,
    "label": "General",
    "note": null,
    "primary_parent": "E660-738",
    "secondary_parents": [],
    "children": [
      "E660",
      "E661.7",
      "E663-664"
    ]
  },
  {
    "id": "E660",
    "code": "E660",
    "prefix": "E",
    "start": 660.0,
    "end": 660.0,
    "label": "Collected works of American statesmen",
    "note": null,
    "primary_parent": "E660-664",
    "secondary_parents": [],
    "children": []
  },
  {
    "id": "E661.7",
    "code": "E661.7",
    "prefix": "E",
    "start": 661.7,
    "end": 661.7,
    "label": "Diplomatic history.  Foreign and general relations",
    "note": null,
    "primary_parent": "E660-664",
    "secondary_parents": [],
    "children": []
  },
  {
    "id": "E663-664",
    "code": "E663-664",
    "prefix": "E",
    "start": 663.0,
    "end": 664.0,
    "label": "Biography",
    "note": null,
    "primary_parent": "E660-664",
    "secondary_parents": [],
    "children": []
  },
  {
    "id": "E666-670",
    "code": "E666-670",
    "prefix": "E",
    "start": 666.0,
    "end": 670.0,
    "label": "Johnson's administration, April 15, 1865-1869",
    "note": null,
    "primary_parent": "E660-738",
    "secondary_parents": [],
    "children": [
      "E668",
      "E669"
    ]
  },
  {
    "id": "E668",
    "code": "E668",
    "prefix": "E",
    "start": 668.0,
    "end": 668.0,
    "label": "Reconstruction, 1865-1877",
    "note": null,
    "primary_parent": "E666-670",
    "secondary_parents": [],
    "children": []
  },
  {
    "id": "E669",
    "code": "E669",
    "prefix": "E",
    "start": 669.0,
    "end": 669.0,
    "label": "Purchase of Alaska, 1867",
    "note": null,
    "primary_parent": "E666-670",
    "secondary_parents": [],
    "children": []
  },
  {
    "id": "E671-680",
    "code": "E671-680",
    "prefix": "E",
    "start": 671.0,
    "end": 680.0,
    "label": "Grant's administrations, 1869-1877",
    "note": null,
    "primary_parent": "E660-738",
    "secondary_parents": [],
    "children": []
  },
  {
    "id": "E681-685",
    "code": "E681-685",
    "prefix": "E",
    "start": 681.0,
    "end": 685.0,
    "label": "Hayes' administration, 1877-1881",
    "note": null,
    "primary_parent": "E660-738",
    "secondary_parents": [],
    "children": []
  },
  {
    "id": "E686-687.9",
    "code": "E686-687.9",
    "prefix": "E",
    "start": 686.0,
    "end": 687.9,
    "label": "Garfield's administration, March 4-September 19, 1881",
    "note": null,
    "primary_parent": "E660-738",
    "secondary_parents": [],
    "children": []
  },
  {
    "id": "E691-695",
    "code": "E691-695",
    "prefix": "E",
    "start": 691.0,
    "end": 695.0,
    "label": "Arthur's administration, September 19, 1881-1885",
    "note": null,
    "primary_parent": "E660-738",
    "secondary_parents": [],
    "children": []
  },
  {
    "id": "E696-700",
    "code": "E696-700",
    "prefix": "E",
    "start": 696.0,
    "end": 700.0,
    "label": "Cleveland's first administration, 1885-1889",
    "note": null,
    "primary_parent": "E660-738",
    "secondary_parents": [],
    "children": []
  },
  {
    "id": "E701-705",
    "code": "E701-705",
    "prefix": "E",
    "start": 701.0,
    "end": 705.0,
    "label": "Benjamin Harrison's administration, 1889-1893",
    "note": null,
    "primary_parent": "E660-738",
    "secondary_parents": [],
    "children": []
  },
  {
    "id": "E706-710",
    "code": "E706-710",
    "prefix": "E",
    "start": 706.0,
    "end": 710.0,
    "label": "Cleveland's second administration, 1893-1897",
    "note": null,
    "primary_parent": "E660-738",
    "secondary_parents": [],
    "children": []
  },
  {
    "id": "E711-738",
    "code": "E711-738",
    "prefix": "E",
    "start": 711.0,
    "end": 738.0,
    "label": "McKinley's first administration, 1897-1901",
    "note": null,
    "primary_parent": "E660-738",
    "secondary_parents": [],
    "children": [
      "E713",
      "E714-735"
    ]
  },
  {
    "id": "E713",
    "code": "E713",
    "prefix": "E",
    "start": 713.0,
    "end": 713.0,
    "label": "Annexation in 1898 of Hawaii, the Philippines, and Puerto Rico",
    "note": null,
    "primary_parent": "E711-738",
    "secondary_parents": [],
    "children": []
  },
  {
    "id": "E714-735",
    "code": "E714-735",
    "prefix": "E",
    "start": 714.0,
    "end": 735.0,
    "label": "War of 1898 (Spanish-American War)",
    "note": null,
    "primary_parent": "E711-738",
    "secondary_parents": [],
    "children": []
  },
  {
    "id": "E740-837.7",
    "code": "E740-837.7",
    "prefix": "E",
    "start": 740.0,
    "end": 837.7,
    "label": "Twentieth century",
    "note": null,
    "primary_parent": "E151-889",
    "secondary_parents": [],
    "children": [
      "E740-749",
      "E751",
      "E756-760",
      "E761-765",
      "E766-783",
      "E784-805",
      "E806-812",
      "E813-816",
      "E835-837.7"
    ]
  },
  {
    "id": "E740-749",
    "code": "E740-749",
    "prefix": "E",
    "start": 740.0,
    "end": 749.0,
    "label": "General",
    "note": null,
    "primary_parent": "E740-837.7",
    "secondary_parents": [],
    "children": [
      "E740.5",
      "E742.5",
      "E743-743.5",
      "E744-744.5",
      "E745",
      "E746",
      "E747-748"
    ]
  },
  {
    "id": "E740.5",
    "code": "E740.5",
    "prefix": "E",
    "start": 740.5,
    "end": 740.5,
    "label": "Sources and documents",
    "note": null,
    "primary_parent": "E740-749",
    "secondary_parents": [],
    "children": []
  },
  {
    "id": "E742.5",
    "code": "E742.5",
    "prefix": "E",
    "start": 742.5,
    "end": 742.5,
    "label": "Collected works of American statesmen",
    "note": null,
    "primary_parent": "E740-749",
    "secondary_parents": [],
    "children": []
  },
  {
    "id": "E743-743.5",
    "code": "E743-743.5",
    "prefix": "E",
    "start": 743.0,
    "end": 743.5,
    "label": "Political history",
    "note": null,
    "primary_parent": "E740-749",
    "secondary_parents": [],
    "children": [
      "E743.5"
    ]
  },
  {
    "id": "E743.5",
    "code": "E743.5",
    "prefix": "E",
    "start": 743.5,
    "end": 743.5,
    "label": "Un-American activities",
    "note": null,
    "primary_parent": "E743-743.5",
    "secondary_parents": [],
    "children": []
  },
  {
    "id": "E744-744.5",
    "code": "E744-744.5",
    "prefix": "E",
    "start": 744.0,
    "end": 744.5,
    "label": "Diplomatic history.  Foreign and general relations",
    "note": null,
    "primary_parent": "E740-749",
    "secondary_parents": [],
    "children": []
  },
  {
    "id": "E745",
    "code": "E745",
    "prefix": "E",
    "start": 745.0,
    "end": 745.0,
    "label": "Military history",
    "note": null,
    "primary_parent": "E740-749",
    "secondary_parents": [],
    "children": []
  },
  {
    "id": "E746",
    "code": "E746",
    "prefix": "E",
    "start": 746.0,
    "end": 746.0,
    "label": "Naval history",
    "note": null,
    "primary_parent": "E740-749",
    "secondary_parents": [],
    "children": []
  },
  {
    "id": "E747-748",
    "code": "E747-748",
    "prefix": "E",
    "start": 747.0,
    "end": 748.0,
    "label": "Biography",
    "note": null,
    "primary_parent": "E740-749",
    "secondary_parents": [],
    "children": []
  },
  {
    "id": "E751",
    "code": "E751",
    "prefix": "E",
    "start": 751.0,
    "end": 751.0,
    "label": "McKinley's second administration, March 4- September 14, 1901",
    "note": null,
    "primary_parent": "E740-837.7",
    "secondary_parents": [],
    "children": []
  },
  {
    "id": "E756-760",
    "code": "E756-760",
    "prefix": "E",
    "start": 756.0,
    "end": 760.0,
    "label": "Theodore Roosevelt's administrations, September 14, 1901-1909",
    "note": null,
    "primary_parent": "E740-837.7",
    "secondary_parents": [],
    "children": []
  },
  {
    "id": "E761-765",
    "code": "E761-765",
    "prefix": "E",
    "start": 761.0,
    "end": 765.0,
    "label": "Taft's administration, 1909-1913",
    "note": null,
    "primary_parent": "E740-837.7",
    "secondary_parents": [],
    "children": []
  },
  {
    "id": "E766-783",
    "code": "E766-783",
    "prefix": "E",
    "start": 766.0,
    "end": 783.0,
    "label": "Wilson's administrations, 1913-1921",
    "note": null,
    "primary_parent": "E740-837.7",
    "secondary_parents": [],
    "children": [
      "E768",
      "E780"
    ]
  },
  {
    "id": "E768",
    "code": "E768",
    "prefix": "E",
    "start": 768.0,
    "end": 768.0,
    "label": "Purchase of Danish West Indies (Virgin Islands), 1917",
    "note": null,
    "primary_parent": "E766-783",
    "secondary_parents": [],
    "children": []
  },
  {
    "id": "E780",
    "code": "E780",
    "prefix": "E",
    "start": 780.0,
    "end": 780.0,
    "label": "Internal history during World War I",
    "note": null,
    "primary_parent": "E766-783",
    "secondary_parents": [],
    "children": []
  },
  {
    "id": "E784-805",
    "code": "E784-805",
    "prefix": "E",
    "start": 784.0,
    "end": 805.0,
    "label": "1919-1933.  Harding-Coolidge-Hoover era.  \"The twenties\"",
    "note": null,
    "primary_parent": "E740-837.7",
    "secondary_parents": [],
    "children": [
      "E785-786",
      "E791-796",
      "E801-805"
    ]
  },
  {
    "id": "E785-786",
    "code": "E785-786",
    "prefix": "E",
    "start": 785.0,
    "end": 786.0,
    "label": "Harding's administration, 1921-August 2, 1923",
    "note": null,
    "primary_parent": "E784-805",
    "secondary_parents": [],
    "children": []
  },
  {
    "id": "E791-796",
    "code": "E791-796",
    "prefix": "E",
    "start": 791.0,
    "end": 796.0,
    "label": "Coolidge's administration, August 2, 1923-1929",
    "note": null,
    "primary_parent": "E784-805",
    "secondary_parents": [],
    "children": []
  },
  {
    "id": "E801-805",
    "code": "E801-805",
    "prefix": "E",
    "start": 801.0,
    "end": 805.0,
    "label": "Hoover's administration, 1919-1933",
    "note": null,
    "primary_parent": "E784-805",
    "secondary_parents": [],
    "children": []
  },
  {
    "id": "E806-812",
    "code": "E806-812",
    "prefix": "E",
    "start": 806.0,
    "end": 812.0,
    "label": "Franklin Delano Roosevelt's administrations, 1933-April 12, 1945",
    "note": null,
    "primary_parent": "E740-837.7",
    "secondary_parents": [],
    "children": []
  },
  {
    "id": "E813-816",
    "code": "E813-816",
    "prefix": "E",
    "start": 813.0,
    "end": 816.0,
    "label": "Truman's administrations, April 12, 1945-1953",
    "note": null,
    "primary_parent": "E740-837.7",
    "secondary_parents": [],
    "children": []
  },
  {
    "id": "E835-837.7",
    "code": "E835-837.7",
    "prefix": "E",
    "start": 835.0,
    "end": 837.7,
    "label": "Eisenhower's administrations, 1953-1961",
    "note": null,
    "primary_parent": "E740-837.7",
    "secondary_parents": [],
    "children": []
  },
  {
    "id": "E838-889",
    "code": "E838-889",
    "prefix": "E",
    "start": 838.0,
    "end": 889.0,
    "label": "Later twentieth century, 1961-2000",
    "note": null,
    "primary_parent": "E151-889",
    "secondary_parents": [],
    "children": [
      "E838-840.8",
      "E841-843",
      "E846-851",
      "E855-861",
      "E865-868",
      "E872-875",
      "E876-880",
      "E881-884",
      "E885-889"
    ]
  },
  {
    "id": "E838-840.8",
    "code": "E838-840.8",
    "prefix": "E",
    "start": 838.0,
    "end": 840.8,
    "label": "General",
    "note": null,
    "primary_parent": "E838-889",
    "secondary_parents": [],
    "children": [
      "E838.3",
      "E839.5-839.8",
      "E840-840.2",
      "E840.6-840.8"
    ]
  },
  {
    "id": "E838.3",
    "code": "E838.3",
    "prefix": "E",
    "start": 838.3,
    "end": 838.3,
    "label": "Sources and documents",
    "note": null,
    "primary_parent": "E838-840.8",
    "secondary_parents": [],
    "children": []
  },
  {
    "id": "E839.5-839.8",
    "code": "E839.5-839.8",
    "prefix": "E",
    "start": 839.5,
    "end": 839.8,
    "label": "Political history",
    "note": null,
    "primary_parent": "E838-840.8",
    "secondary_parents": [],
    "children": [
      "E839.8"
    ]
  },
  {
    "id": "E839.8",
    "code": "E839.8",
    "prefix": "E",
    "start": 839.8,
    "end": 839.8,
    "label": "Un-American activities",
    "note": null,
    "primary_parent": "E839.5-839.8",
    "secondary_parents": [],
    "children": []
  },
  {
    "id": "E840-840.2",
    "code": "E840-840.2",
    "prefix": "E",
    "start": 840.0,
    "end": 840.2,
    "label": "Diplomatic history.  Foreign and general relations",
    "note": null,
    "primary_parent": "E838-840.8",
    "secondary_parents": [],
    "children": []
  },
  {
    "id": "E840.6-840.8",
    "code": "E840.6-840.8",
    "prefix": "E",
    "start": 840.6,
    "end": 840.8,
    "label": "Biography (General)",
    "note": null,
    "primary_parent": "E838-840.8",
    "secondary_parents": [],
    "children": []
  },
  {
    "id": "E841-843",
    "code": "E841-843",
    "prefix": "E",
    "start": 841.0,
    "end": 843.0,
    "label": "Kennedy's administration, 1961-November 22, 1963",
    "note": null,
    "primary_parent": "E838-889",
    "secondary_parents": [],
    "children": [
      "E842.9"
    ]
  },
  {
    "id": "E842.9",
    "code": "E842.9",
    "prefix": "E",
    "start": 842.9,
    "end": 842.9,
    "label": "Assassination, funeral, memorial services, etc.",
    "note": null,
    "primary_parent": "E841-843",
    "secondary_parents": [],
    "children": []
  },
  {
    "id": "E846-851",
    "code": "E846-851",
    "prefix": "E",
    "start": 846.0,
    "end": 851.0,
    "label": "Johnson's administrations, November 22, 1963-1969",
    "note": null,
    "primary_parent": "E838-889",
    "secondary_parents": [],
    "children": []
  },
  {
    "id": "E855-861",
    "code": "E855-861",
    "prefix": "E",
    "start": 855.0,
    "end": 861.0,
    "label": "Nixon's administrations, 1969-August 9, 1974",
    "note": null,
    "primary_parent": "E838-889",
    "secondary_parents": [],
    "children": [
      "E860-861"
    ]
  },
  {
    "id": "E860-861",
    "code": "E860-861",
    "prefix": "E",
    "start": 860.0,
    "end": 861.0,
    "label": "Watergate Affair.  Resignation",
    "note": null,
    "primary_parent": "E855-861",
    "secondary_parents": [],
    "children": []
  },
  {
    "id": "E865-868",
    "code": "E865-868",
    "prefix": "E",
    "start": 865.0,
    "end": 868.0,
    "label": "Ford's administration, August 9, 1974-1977",
    "note": null,
    "primary_parent": "E838-889",
    "secondary_parents": [],
    "children": []
  },
  {
    "id": "E872-875",
    "code": "E872-875",
    "prefix": "E",
    "start": 872.0,
    "end": 875.0,
    "label": "Carter's administration, 1977-1981",
    "note": null,
    "primary_parent": "E838-889",
    "secondary_parents": [],
    "children": []
  },
  {
    "id": "E876-880",
    "code": "E876-880",
    "prefix": "E",
    "start": 876.0,
    "end": 880.0,
    "label": "Reagan's administrations, 1981-1989",
    "note": null,
    "primary_parent": "E838-889",
    "secondary_parents": [],
    "children": [
      "E877.3"
    ]
  },
  {
    "id": "E877.3",
    "code": "E877.3",
    "prefix": "E",
    "start": 877.3,
    "end": 877.3,
    "label": "Assassination attempt",
    "note": null,
    "primary_parent": "E876-880",
    "secondary_parents": [],
    "children": []
  },
  {
    "id": "E881-884",
    "code": "E881-884",
    "prefix": "E",
    "start": 881.0,
    "end": 884.0,
    "label": "George H.W. Bush's administration, 1989-1993",
    "note": null,
    "primary_parent": "E838-889",
    "secondary_parents": [],
    "children": []
  },
  {
    "id": "E885-889",
    "code": "E885-889",
    "prefix": "E",
    "start": 885.0,
    "end": 889.0,
    "label": "Clinton's administrations, 1993-2001",
    "note": null,
    "primary_parent": "E838-889",
    "secondary_parents": [],
    "children": []
  },
  {
    "id": "E895-904",
    "code": "E895-904",
    "prefix": "E",
    "start": 895.0,
    "end": 904.0,
    "label": "Twenty-first century",
    "note": null,
    "primary_parent": null,
    "secondary_parents": [],
    "children": []
  },
  {
    "id": "E902-906",
    "code": "E902-906",
    "prefix": "E",
    "start": 902.0,
    "end": 906.0,
    "label": "George W. Bush's administrations, 2001-2009",
    "note": null,
    "primary_parent": null,
    "secondary_parents": [],
    "children": []
  },
  {
    "id": "E907-909",
    "code": "E907-909",
    "prefix": "E",
    "start": 907.0,
    "end": 909.0,
    "label": "Barack Obama's administration, 2009-",
    "note": null,
    "primary_parent": null,
    "secondary_parents": [],
    "children": []
  },
  {
    "id": "F1-975",
    "code": "F1-975",
    "prefix": "F",
    "start": 1.0,
    "end": 975.0,
    "label": "United States local history",
    "note": null,
    "primary_parent": null,
    "secondary_parents": [],
    "children": [
      "F1-15",
      "F16-30",
      "F31-45",
      "F46-60",
      "F61-75",
      "F76-90",
      "F91-105",
      "F106",
      "F116-130",
      "F131-145",
      "F146-160",
      "F161-175",
      "F176-190",
      "F191-205",
      "F206-220",
      "F221-235",
      "F236-250",
      "F251-265",
      "F266-280",
      "F281-295",
      "F296-301",
      "F306-320",
      "F321-335",
      "F336-350",
      "F350.5-355",
      "F366-380",
      "F381-395",
      "F396",
      "F406-420",
      "F431-445",
      "F446-460",
      "F461-475",
      "F476-485",
      "F486-500",
      "F516-520",
      "F521-535",
      "F536-550",
      "F550.5-553.2",
      "F561-575",
      "F576-590",
      "F590.3-596.3",
      "F597",
      "F598",
      "F601-615",
      "F616-630",
      "F631-645",
      "F646-660",
      "F661-675",
      "F676-690",
      "F691-705",
      "F721-722",
      "F726-740",
      "F741-755",
      "F756-770",
      "F771-785",
      "F786-790",
      "F791-805",
      "F806-820",
      "F821-835",
      "F836-850",
      "F850.5-851.5",
      "F851.7",
      "F852-854",
      "F856-870",
      "F871-885",
      "F886-900",
      "F901-951",
      "F965",
      "F970",
      "F975"
    ]
  },
  {
    "id": "F1-15",
    "code": "F1-15",
    "prefix": "F",
    "start": 1.0,
    "end": 15.0,
    "label": "New England",
    "note": null,
    "primary_parent": "F1-975",
    "secondary_parents": [],
    "children": []
  },
  {
    "id": "F16-30",
    "code": "F16-30",
    "prefix": "F",
    "start": 16.0,
    "end": 30.0,
    "label": "Maine",
    "note": null,
    "primary_parent": "F1-975",
    "secondary_parents": [],
    "children": []
  },
  {
    "id": "F31-45",
    "code": "F31-45",
    "prefix": "F",
    "start": 31.0,
    "end": 45.0,
    "label": "New Hampshire",
    "note": null,
    "primary_parent": "F1-975",
    "secondary_parents": [],
    "children": []
  },
  {
    "id": "F46-60",
    "code": "F46-60",
    "prefix": "F",
    "start": 46.0,
    "end": 60.0,
    "label": "Vermont",
    "note": null,
    "primary_parent": "F1-975",
    "secondary_parents": [],
    "children": []
  },
  {
    "id": "F61-75",
    "code": "F61-75",
    "prefix": "F",
    "start": 61.0,
    "end": 75.0,
    "label": "Massachusetts",
    "note": null,
    "primary_parent": "F1-975",
    "secondary_parents": [],
    "children": []
  },
  {
    "id": "F76-90",
    "code": "F76-90",
    "prefix": "F",
    "start": 76.0,
    "end": 90.0,
    "label": "Rhode Island",
    "note": null,
    "primary_parent": "F1-975",
    "secondary_parents": [],
    "children": []
  },
  {
    "id": "F91-105",
    "code": "F91-105",
    "prefix": "F",
    "start": 91.0,
    "end": 105.0,
    "label": "Connecticut",
    "note": null,
    "primary_parent": "F1-975",
    "secondary_parents": [],
    "children": []
  },
  {
    "id": "F106",
    "code": "F106",
    "prefix": "F",
    "start": 106.0,
    "end": 106.0,
    "label": "Atlantic coast.  Middle Atlantic States",
    "note": null,
    "primary_parent": "F1-975",
    "secondary_parents": [],
    "children": []
  },
  {
    "id": "F116-130",
    "code": "F116-130",
    "prefix": "F",
    "start": 116.0,
    "end": 130.0,
    "label": "New York",
    "note": null,
    "primary_parent": "F1-975",
    "secondary_parents": [],
    "children": []
  },
  {
    "id": "F131-145",
    "code": "F131-145",
    "prefix": "F",
    "start": 131.0,
    "end": 145.0,
    "label": "New Jersey",
    "note": null,
    "primary_parent": "F1-975",
    "secondary_parents": [],
    "children": []
  },
  {
    "id": "F146-160",
    "code": "F146-160",
    "prefix": "F",
    "start": 146.0,
    "end": 160.0,
    "label": "Pennsylvania",
    "note": null,
    "primary_parent": "F1-975",
    "secondary_parents": [],
    "children": []
  },
  {
    "id": "F161-175",
    "code": "F161-175",
    "prefix": "F",
    "start": 161.0,
    "end": 175.0,
    "label": "Delaware",
    "note": null,
    "primary_parent": "F1-975",
    "secondary_parents": [],
    "children": []
  },
  {
    "id": "F176-190",
    "code": "F176-190",
    "prefix": "F",
    "start": 176.0,
    "end": 190.0,
    "label": "Maryland",
    "note": null,
    "primary_parent": "F1-975",
    "secondary_parents": [],
    "children": []
  },
  {
    "id": "F191-205",
    "code": "F191-205",
    "prefix": "F",
    "start": 191.0,
    "end": 205.0,
    "label": "District of Columbia.  Washington",
    "note": null,
    "primary_parent": "F1-975",
    "secondary_parents": [],
    "children": []
  },
  {
    "id": "F206-220",
    "code": "F206-220",
    "prefix": "F",
    "start": 206.0,
    "end": 220.0,
    "label": "The South.  South Atlantic States",
    "note": null,
    "primary_parent": "F1-975",
    "secondary_parents": [],
    "children": []
  },
  {
    "id": "F221-235",
    "code": "F221-235",
    "prefix": "F",
    "start": 221.0,
    "end": 235.0,
    "label": "Virginia",
    "note": null,
    "primary_parent": "F1-975",
    "secondary_parents": [],
    "children": []
  },
  {
    "id": "F236-250",
    "code": "F236-250",
    "prefix": "F",
    "start": 236.0,
    "end": 250.0,
    "label": "West Virginia",
    "note": null,
    "primary_parent": "F1-975",
    "secondary_parents": [],
    "children": []
  },
  {
    "id": "F251-265",
    "code": "F251-265",
    "prefix": "F",
    "start": 251.0,
    "end": 265.0,
    "label": "North Carolina",
    "note": null,
    "primary_parent": "F1-975",
    "secondary_parents": [],
    "children": []
  },
  {
    "id": "F266-280",
    "code": "F266-280",
    "prefix": "F",
    "start": 266.0,
    "end": 280.0,
    "label": "South Carolina",
    "note": null,
    "primary_parent": "F1-975",
    "secondary_parents": [],
    "children": []
  },
  {
    "id": "F281-295",
    "code": "F281-295",
    "prefix": "F",
    "start": 281.0,
    "end": 295.0,
    "label": "Georgia",
    "note": null,
    "primary_parent": "F1-975",
    "secondary_parents": [],
    "children": []
  },
  {
    "id": "F296-301",
    "code": "F296-301",
    "prefix": "F",
    "start": 296.0,
    "end": 301.0,
    "label": "Gulf States.  West Florida",
    "note": null,
    "primary_parent": "F1-975",
    "secondary_parents": [],
    "children": []
  },
  {
    "id": "F306-320",
    "code": "F306-320",
    "prefix": "F",
    "start": 306.0,
    "end": 320.0,
    "label": "Florida",
    "note": null,
    "primary_parent": "F1-975",
    "secondary_parents": [],
    "children": []
  },
  {
    "id": "F321-335",
    "code": "F321-335",
    "prefix": "F",
    "start": 321.0,
    "end": 335.0,
    "label": "Alabama",
    "note": null,
    "primary_parent": "F1-975",
    "secondary_parents": [],
    "children": []
  },
  {
    "id": "F336-350",
    "code": "F336-350",
    "prefix": "F",
    "start": 336.0,
    "end": 350.0,
    "label": "Mississippi",
    "note": null,
    "primary_parent": "F1-975",
    "secondary_parents": [],
    "children": []
  },
  {
    "id": "F350.5-355",
    "code": "F350.5-355",
    "prefix": "F",
    "start": 350.5,
    "end": 355.0,
    "label": "Mississippi River and Valley.  Middle West",
    "note": null,
    "primary_parent": "F1-975",
    "secondary_parents": [],
    "children": []
  },
  {
    "id": "F366-380",
    "code": "F366-380",
    "prefix": "F",
    "start": 366.0,
    "end": 380.0,
    "label": "Louisiana",
    "note": null,
    "primary_parent": "F1-975",
    "secondary_parents": [],
    "children": []
  },
  {
    "id": "F381-395",
    "code": "F381-395",
    "prefix": "F",
    "start": 381.0,
    "end": 395.0,
    "label": "Texas",
    "note": null,
    "primary_parent": "F1-975",
    "secondary_parents": [],
    "children": []
  },
  {
    "id": "F396",
    "code": "F396",
    "prefix": "F",
    "start": 396.0,
    "end": 396.0,
    "label": "Old Southwest.  Lower Mississippi Valley",
    "note": null,
    "primary_parent": "F1-975",
    "secondary_parents": [],
    "children": []
  },
  {
    "id": "F406-420",
    "code": "F406-420",
    "prefix": "F",
    "start": 406.0,
    "end": 420.0,
    "label": "Arkansas",
    "note": null,
    "primary_parent": "F1-975",
    "secondary_parents": [],
    "children": []
  },
  {
    "id": "F431-445",
    "code": "F431-445",
    "prefix": "F",
    "start": 431.0,
    "end": 445.0,
    "label": "Tennessee",
    "note": null,
    "primary_parent": "F1-975",
    "secondary_parents": [],
    "children": []
  },
  {
    "id": "F446-460",
    "code": "F446-460",
    "prefix": "F",
    "start": 446.0,
    "end": 460.0,
    "label": "Kentucky",
    "note": null,
    "primary_parent": "F1-975",
    "secondary_parents": [],
    "children": []
  },
  {
    "id": "F461-475",
    "code": "F461-475",
    "prefix": "F",
    "start": 461.0,
    "end": 475.0,
    "label": "Missouri",
    "note": null,
    "primary_parent": "F1-975",
    "secondary_parents": [],
    "children": []
  },
  {
    "id": "F476-485",
    "code": "F476-485",
    "prefix": "F",
    "start": 476.0,
    "end": 485.0,
    "label": "Old Northwest.  Northwest Territory",
    "note": null,
    "primary_parent": "F1-975",
    "secondary_parents": [],
    "children": []
  },
  {
    "id": "F486-500",
    "code": "F486-500",
    "prefix": "F",
    "start": 486.0,
    "end": 500.0,
    "label": "Ohio",
    "note": null,
    "primary_parent": "F1-975",
    "secondary_parents": [],
    "children": []
  },
  {
    "id": "F516-520",
    "code": "F516-520",
    "prefix": "F",
    "start": 516.0,
    "end": 520.0,
    "label": "Ohio River and Valley",
    "note": null,
    "primary_parent": "F1-975",
    "secondary_parents": [],
    "children": []
  },
  {
    "id": "F521-535",
    "code": "F521-535",
    "prefix": "F",
    "start": 521.0,
    "end": 535.0,
    "label": "Indiana",
    "note": null,
    "primary_parent": "F1-975",
    "secondary_parents": [],
    "children": []
  },
  {
    "id": "F536-550",
    "code": "F536-550",
    "prefix": "F",
    "start": 536.0,
    "end": 550.0,
    "label": "Illinois",
    "note": null,
    "primary_parent": "F1-975",
    "secondary_parents": [],
    "children": []
  },
  {
    "id": "F550.5-553.2",
    "code": "F550.5-553.2",
    "prefix": "F",
    "start": 550.5,
    "end": 553.2,
    "label": "The Lake region.  Great Lakes",
    "note": null,
    "primary_parent": "F1-975",
    "secondary_parents": [],
    "children": []
  },
  {
    "id": "F561-575",
    "code": "F561-575",
    "prefix": "F",
    "start": 561.0,
    "end": 575.0,
    "label": "Michigan",
    "note": null,
    "primary_parent": "F1-975",
    "secondary_parents": [],
    "children": []
  },
  {
    "id": "F576-590",
    "code": "F576-590",
    "prefix": "F",
    "start": 576.0,
    "end": 590.0,
    "label": "Wisconsin",
    "note": null,
    "primary_parent": "F1-975",
    "secondary_parents": [],
    "children": []
  },
  {
    "id": "F590.3-596.3",
    "code": "F590.3-596.3",
    "prefix": "F",
    "start": 590.3,
    "end": 596.3,
    "label": "The West.  Trans-Mississippi Region.  Great Plains",
    "note": null,
    "primary_parent": "F1-975",
    "secondary_parents": [],
    "children": []
  },
  {
    "id": "F597",
    "code": "F597",
    "prefix": "F",
    "start": 597.0,
    "end": 597.0,
    "label": "The Northwest",
    "note": null,
    "primary_parent": "F1-975",
    "secondary_parents": [],
    "children": []
  },
  {
    "id": "F598",
    "code": "F598",
    "prefix": "F",
    "start": 598.0,
    "end": 598.0,
    "label": "Missouri River and Valley",
    "note": null,
    "primary_parent": "F1-975",
    "secondary_parents": [],
    "children": []
  },
  {
    "id": "F601-615",
    "code": "F601-615",
    "prefix": "F",
    "start": 601.0,
    "end": 615.0,
    "label": "Minnesota",
    "note": null,
    "primary_parent": "F1-975",
    "secondary_parents": [],
    "children": []
  },
  {
    "id": "F616-630",
    "code": "F616-630",
    "prefix": "F",
    "start": 616.0,
    "end": 630.0,
    "label": "Iowa",
    "note": null,
    "primary_parent": "F1-975",
    "secondary_parents": [],
    "children": []
  },
  {
    "id": "F631-645",
    "code": "F631-645",
    "prefix": "F",
    "start": 631.0,
    "end": 645.0,
    "label": "North Dakota",
    "note": null,
    "primary_parent": "F1-975",
    "secondary_parents": [],
    "children": []
  },
  {
    "id": "F646-660",
    "code": "F646-660",
    "prefix": "F",
    "start": 646.0,
    "end": 660.0,
    "label": "South Dakota",
    "note": null,
    "primary_parent": "F1-975",
    "secondary_parents": [],
    "children": []
  },
  {
    "id": "F661-675",
    "code": "F661-675",
    "prefix": "F",
    "start": 661.0,
    "end": 675.0,
    "label": "Nebraska",
    "note": null,
    "primary_parent": "F1-975",
    "secondary_parents": [],
    "children": []
  },
  {
    "id": "F676-690",
    "code": "F676-690",
    "prefix": "F",
    "start": 676.0,
    "end": 690.0,
    "label": "Kansas",
    "note": null,
    "primary_parent": "F1-975",
    "secondary_parents": [],
    "children": []
  },
  {
    "id": "F691-705",
    "code": "F691-705",
    "prefix": "F",
    "start": 691.0,
    "end": 705.0,
    "label": "Oklahoma",
    "note": null,
    "primary_parent": "F1-975",
    "secondary_parents": [],
    "children": []
  },
  {
    "id": "F721-722",
    "code": "F721-722",
    "prefix": "F",
    "start": 721.0,
    "end": 722.0,
    "label": "Rocky Mountains.  Yellowstone National Park",
    "note": null,
    "primary_parent": "F1-975",
    "secondary_parents": [],
    "children": []
  },
  {
    "id": "F726-740",
    "code": "F726-740",
    "prefix": "F",
    "start": 726.0,
    "end": 740.0,
    "label": "Montana",
    "note": null,
    "primary_parent": "F1-975",
    "secondary_parents": [],
    "children": []
  },
  {
    "id": "F741-755",
    "code": "F741-755",
    "prefix": "F",
    "start": 741.0,
    "end": 755.0,
    "label": "Idaho",
    "note": null,
    "primary_parent": "F1-975",
    "secondary_parents": [],
    "children": []
  },
  {
    "id": "F756-770",
    "code": "F756-770",
    "prefix": "F",
    "start": 756.0,
    "end": 770.0,
    "label": "Wyoming",
    "note": null,
    "primary_parent": "F1-975",
    "secondary_parents": [],
    "children": []
  },
  {
    "id": "F771-785",
    "code": "F771-785",
    "prefix": "F",
    "start": 771.0,
    "end": 785.0,
    "label": "Colorado",
    "note": null,
    "primary_parent": "F1-975",
    "secondary_parents": [],
    "children": []
  },
  {
    "id": "F786-790",
    "code": "F786-790",
    "prefix": "F",
    "start": 786.0,
    "end": 790.0,
    "label": "New Southwest.  Colorado River, Canyon, and Valley",
    "note": null,
    "primary_parent": "F1-975",
    "secondary_parents": [],
    "children": []
  },
  {
    "id": "F791-805",
    "code": "F791-805",
    "prefix": "F",
    "start": 791.0,
    "end": 805.0,
    "label": "New Mexico",
    "note": null,
    "primary_parent": "F1-975",
    "secondary_parents": [],
    "children": []
  },
  {
    "id": "F806-820",
    "code": "F806-820",
    "prefix": "F",
    "start": 806.0,
    "end": 820.0,
    "label": "Arizona",
    "note": null,
    "primary_parent": "F1-975",
    "secondary_parents": [],
    "children": []
  },
  {
    "id": "F821-835",
    "code": "F821-835",
    "prefix": "F",
    "start": 821.0,
    "end": 835.0,
    "label": "Utah",
    "note": null,
    "primary_parent": "F1-975",
    "secondary_parents": [],
    "children": []
  },
  {
    "id": "F836-850",
    "code": "F836-850",
    "prefix": "F",
    "start": 836.0,
    "end": 850.0,
    "label": "Nevada",
    "note": null,
    "primary_parent": "F1-975",
    "secondary_parents": [],
    "children": []
  },
  {
    "id": "F850.5-851.5",
    "code": "F850.5-851.5",
    "prefix": "F",
    "start": 850.5,
    "end": 851.5,
    "label": "Pacific States",
    "note": null,
    "primary_parent": "F1-975",
    "secondary_parents": [],
    "children": []
  },
  {
    "id": "F851.7",
    "code": "F851.7",
    "prefix": "F",
    "start": 851.7,
    "end": 851.7,
    "label": "Cascade Range",
    "note": null,
    "primary_parent": "F1-975",
    "secondary_parents": [],
    "children": []
  },
  {
    "id": "F852-854",
    "code": "F852-854",
    "prefix": "F",
    "start": 852.0,
    "end": 854.0,
    "label": "Pacific Northwest.  Columbia River and Valley.",
    "note": null,
    "primary_parent": "F1-975",
    "secondary_parents": [],
    "children": []
  },
  {
    "id": "F856-870",
    "code": "F856-870",
    "prefix": "F",
    "start": 856.0,
    "end": 870.0,
    "label": "California",
    "note": null,
    "primary_parent": "F1-975",
    "secondary_parents": [],
    "children": []
  },
  {
    "id": "F871-885",
    "code": "F871-885",
    "prefix": "F",
    "start": 871.0,
    "end": 885.0,
    "label": "Oregon",
    "note": null,
    "primary_parent": "F1-975",
    "secondary_parents": [],
    "children": []
  },
  {
    "id": "F886-900",
    "code": "F886-900",
    "prefix": "F",
    "start": 886.0,
    "end": 900.0,
    "label": "Washington",
    "note": null,
    "primary_parent": "F1-975",
    "secondary_parents": [],
    "children": []
  },
  {
    "id": "F901-951",
    "code": "F901-951",
    "prefix": "F",
    "start": 901.0,
    "end": 951.0,
    "label": "Alaska",
    "note": null,
    "primary_parent": "F1-975",
    "secondary_parents": [],
    "children": [
      "F951"
    ]
  },
  {
    "id": "F951",
    "code": "F951",
    "prefix": "F",
    "start": 951.0,
    "end": 951.0,
    "label": "Bering Sea and Aleutian Islands Hawaii, see DU620+",
    "note": null,
    "primary_parent": "F901-951",
    "secondary_parents": [],
    "children": []
  },
  {
    "id": "F965",
    "code": "F965",
    "prefix": "F",
    "start": 965.0,
    "end": 965.0,
    "label": "The territories of the United States (General) United States local history - Continued",
    "note": null,
    "primary_parent": "F1-975",
    "secondary_parents": [],
    "children": []
  },
  {
    "id": "F970",
    "code": "F970",
    "prefix": "F",
    "start": 970.0,
    "end": 970.0,
    "label": "Insular possessions of the United States (General)",
    "note": null,
    "primary_parent": "F1-975",
    "secondary_parents": [],
    "children": []
  },
  {
    "id": "F975",
    "code": "F975",
    "prefix": "F",
    "start": 975.0,
    "end": 975.0,
    "label": "Central American, West Indian, and other countries",
    "note": null,
    "primary_parent": "F1-975",
    "secondary_parents": [],
    "children": []
  },
  {
    "id": "F1001-1145.2",
    "code": "F1001-1145.2",
    "prefix": "F",
    "start": 1001.0,
    "end": 1145.2,
    "label": "British America",
    "note": null,
    "primary_parent": "F1001-1145.2",
    "secondary_parents": [],
    "children": [
      "F1001-1145.2",
      "F1001-1035",
      "F1035.8",
      "F1036-1040",
      "F1041-1045",
      "F1046-1049.7",
      "F1050",
      "F1051-1055",
      "F1056-1059.7",
      "F1060-1060.97",
      "F1061-1065",
      "F1067",
      "F1070-1074.7",
      "F1075-1080",
      "F1086-1089.7",
      "F1090",
      "F1090.5",
      "F1091-1095.5",
      "F1096-1100.5",
      "F1101-1105.7",
      "F1106-1110.5",
      "F1121-1139",
      "F1140",
      "F1141-1145.2"
    ]
  },
  {
    "id": "F1001-1145.2",
    "code": "F1001-1145.2",
    "prefix": "F",
    "start": 1001.0,
    "end": 1145.2,
    "label": "Canada",
    "note": null,
    "primary_parent": "F1001-1145.2",
    "secondary_parents": [],
    "children": [
      "F1001-1145.2"
    ]
  },
  {
    "id": "F1001-1035",
    "code": "F1001-1035",
    "prefix": "F",
    "start": 1001.0,
    "end": 1035.0,
    "label": "General",
    "note": null,
    "primary_parent": "F1001-1145.2",
    "secondary_parents": [],
    "children": []
  },
  {
    "id": "F1035.8",
    "code": "F1035.8",
    "prefix": "F",
    "start": 1035.8,
    "end": 1035.8,
    "label": "Maritime provinces.  Atlantic coast of Canada",
    "note": null,
    "primary_parent": "F1001-1145.2",
    "secondary_parents": [],
    "children": []
  },
  {
    "id": "F1036-1040",
    "code": "F1036-1040",
    "prefix": "F",
    "start": 1036.0,
    "end": 1040.0,
    "label": "Nova Scotia.  Acadia",
    "note": null,
    "primary_parent": "F1001-1145.2",
    "secondary_parents": [],
    "children": []
  },
  {
    "id": "F1041-1045",
    "code": "F1041-1045",
    "prefix": "F",
    "start": 1041.0,
    "end": 1045.0,
    "label": "New Brunswick",
    "note": null,
    "primary_parent": "F1001-1145.2",
    "secondary_parents": [],
    "children": []
  },
  {
    "id": "F1046-1049.7",
    "code": "F1046-1049.7",
    "prefix": "F",
    "start": 1046.0,
    "end": 1049.7,
    "label": "Prince Edward Island",
    "note": null,
    "primary_parent": "F1001-1145.2",
    "secondary_parents": [],
    "children": []
  },
  {
    "id": "F1050",
    "code": "F1050",
    "prefix": "F",
    "start": 1050.0,
    "end": 1050.0,
    "label": "St. Lawrence Gulf, River and Valley (General)",
    "note": null,
    "primary_parent": "F1001-1145.2",
    "secondary_parents": [],
    "children": []
  },
  {
    "id": "F1051-1055",
    "code": "F1051-1055",
    "prefix": "F",
    "start": 1051.0,
    "end": 1055.0,
    "label": "Quebec",
    "note": null,
    "primary_parent": "F1001-1145.2",
    "secondary_parents": [],
    "children": []
  },
  {
    "id": "F1056-1059.7",
    "code": "F1056-1059.7",
    "prefix": "F",
    "start": 1056.0,
    "end": 1059.7,
    "label": "Ontario",
    "note": null,
    "primary_parent": "F1001-1145.2",
    "secondary_parents": [],
    "children": []
  },
  {
    "id": "F1060-1060.97",
    "code": "F1060-1060.97",
    "prefix": "F",
    "start": 1060.0,
    "end": 1060.97,
    "label": "Canadian Northwest.  Northwest Territories",
    "note": null,
    "primary_parent": "F1001-1145.2",
    "secondary_parents": [],
    "children": []
  },
  {
    "id": "F1061-1065",
    "code": "F1061-1065",
    "prefix": "F",
    "start": 1061.0,
    "end": 1065.0,
    "label": "Manitoba",
    "note": null,
    "primary_parent": "F1001-1145.2",
    "secondary_parents": [],
    "children": []
  },
  {
    "id": "F1067",
    "code": "F1067",
    "prefix": "F",
    "start": 1067.0,
    "end": 1067.0,
    "label": "Assiniboia",
    "note": null,
    "primary_parent": "F1001-1145.2",
    "secondary_parents": [],
    "children": []
  },
  {
    "id": "F1070-1074.7",
    "code": "F1070-1074.7",
    "prefix": "F",
    "start": 1070.0,
    "end": 1074.7,
    "label": "Saskatchewan",
    "note": null,
    "primary_parent": "F1001-1145.2",
    "secondary_parents": [],
    "children": []
  },
  {
    "id": "F1075-1080",
    "code": "F1075-1080",
    "prefix": "F",
    "start": 1075.0,
    "end": 1080.0,
    "label": "Alberta",
    "note": null,
    "primary_parent": "F1001-1145.2",
    "secondary_parents": [],
    "children": []
  },
  {
    "id": "F1086-1089.7",
    "code": "F1086-1089.7",
    "prefix": "F",
    "start": 1086.0,
    "end": 1089.7,
    "label": "British Columbia",
    "note": null,
    "primary_parent": "F1001-1145.2",
    "secondary_parents": [],
    "children": []
  },
  {
    "id": "F1090",
    "code": "F1090",
    "prefix": "F",
    "start": 1090.0,
    "end": 1090.0,
    "label": "Rocky Mountains of Canada",
    "note": null,
    "primary_parent": "F1001-1145.2",
    "secondary_parents": [],
    "children": []
  },
  {
    "id": "F1090.5",
    "code": "F1090.5",
    "prefix": "F",
    "start": 1090.5,
    "end": 1090.5,
    "label": "Arctic regions",
    "note": null,
    "primary_parent": "F1001-1145.2",
    "secondary_parents": [],
    "children": []
  },
  {
    "id": "F1091-1095.5",
    "code": "F1091-1095.5",
    "prefix": "F",
    "start": 1091.0,
    "end": 1095.5,
    "label": "Yukon",
    "note": null,
    "primary_parent": "F1001-1145.2",
    "secondary_parents": [],
    "children": []
  },
  {
    "id": "F1096-1100.5",
    "code": "F1096-1100.5",
    "prefix": "F",
    "start": 1096.0,
    "end": 1100.5,
    "label": "Mackenzie",
    "note": null,
    "primary_parent": "F1001-1145.2",
    "secondary_parents": [],
    "children": []
  },
  {
    "id": "F1101-1105.7",
    "code": "F1101-1105.7",
    "prefix": "F",
    "start": 1101.0,
    "end": 1105.7,
    "label": "Franklin",
    "note": null,
    "primary_parent": "F1001-1145.2",
    "secondary_parents": [],
    "children": []
  },
  {
    "id": "F1106-1110.5",
    "code": "F1106-1110.5",
    "prefix": "F",
    "start": 1106.0,
    "end": 1110.5,
    "label": "Keewatin",
    "note": null,
    "primary_parent": "F1001-1145.2",
    "secondary_parents": [],
    "children": []
  },
  {
    "id": "F1121-1139",
    "code": "F1121-1139",
    "prefix": "F",
    "start": 1121.0,
    "end": 1139.0,
    "label": "Newfoundland",
    "note": null,
    "primary_parent": "F1001-1145.2",
    "secondary_parents": [],
    "children": [
      "F1135-1139"
    ]
  },
  {
    "id": "F1135-1139",
    "code": "F1135-1139",
    "prefix": "F",
    "start": 1135.0,
    "end": 1139.0,
    "label": "Labrador",
    "note": null,
    "primary_parent": "F1121-1139",
    "secondary_parents": [],
    "children": []
  },
  {
    "id": "F1140",
    "code": "F1140",
    "prefix": "F",
    "start": 1140.0,
    "end": 1140.0,
    "label": "The Labrador Peninsula",
    "note": null,
    "primary_parent": "F1001-1145.2",
    "secondary_parents": [],
    "children": []
  },
  {
    "id": "F1141-1145.2",
    "code": "F1141-1145.2",
    "prefix": "F",
    "start": 1141.0,
    "end": 1145.2,
    "label": "Nunavut",
    "note": null,
    "primary_parent": "F1001-1145.2",
    "secondary_parents": [],
    "children": []
  },
  {
    "id": "F1170",
    "code": "F1170",
    "prefix": "F",
    "start": 1170.0,
    "end": 1170.0,
    "label": "Saint Pierre and Miquelon Other French America",
    "note": null,
    "primary_parent": null,
    "secondary_parents": [],
    "children": []
  },
  {
    "id": "F1201-3799",
    "code": "F1201-3799",
    "prefix": "F",
    "start": 1201.0,
    "end": 3799.0,
    "label": "Latin America.  Spanish America",
    "note": null,
    "primary_parent": null,
    "secondary_parents": [],
    "children": [
      "F1201-1392",
      "F1401-1419",
      "F1421-1440",
      "F1441-1457",
      "F1461-1477",
      "F1481-1497",
      "F1501-1517",
      "F1521-1537",
      "F1541-1557",
      "F1561-1577",
      "F1630-1640",
      "F1650-1660",
      "F1741-1991",
      "F2001-2151",
      "F2155-2191",
      "F2201-3799"
    ]
  },
  {
    "id": "F1201-1392",
    "code": "F1201-1392",
    "prefix": "F",
    "start": 1201.0,
    "end": 1392.0,
    "label": "Mexico",
    "note": null,
    "primary_parent": "F1201-3799",
    "secondary_parents": [],
    "children": [
      "F1218.5-1221"
    ]
  },
  {
    "id": "F1218.5-1221",
    "code": "F1218.5-1221",
    "prefix": "F",
    "start": 1218.5,
    "end": 1221.0,
    "label": "Antiquities.  Indians",
    "note": null,
    "primary_parent": "F1201-1392",
    "secondary_parents": [],
    "children": []
  },
  {
    "id": "F1401-1419",
    "code": "F1401-1419",
    "prefix": "F",
    "start": 1401.0,
    "end": 1419.0,
    "label": "Latin America (General)",
    "note": null,
    "primary_parent": "F1201-3799",
    "secondary_parents": [],
    "children": []
  },
  {
    "id": "F1421-1440",
    "code": "F1421-1440",
    "prefix": "F",
    "start": 1421.0,
    "end": 1440.0,
    "label": "Central America",
    "note": null,
    "primary_parent": "F1201-3799",
    "secondary_parents": [],
    "children": [
      "F1435-1435.3"
    ]
  },
  {
    "id": "F1435-1435.3",
    "code": "F1435-1435.3",
    "prefix": "F",
    "start": 1435.0,
    "end": 1435.3,
    "label": "Mayas",
    "note": null,
    "primary_parent": "F1421-1440",
    "secondary_parents": [],
    "children": []
  },
  {
    "id": "F1441-1457",
    "code": "F1441-1457",
    "prefix": "F",
    "start": 1441.0,
    "end": 1457.0,
    "label": "Belize",
    "note": null,
    "primary_parent": "F1201-3799",
    "secondary_parents": [],
    "children": []
  },
  {
    "id": "F1461-1477",
    "code": "F1461-1477",
    "prefix": "F",
    "start": 1461.0,
    "end": 1477.0,
    "label": "Guatemala",
    "note": null,
    "primary_parent": "F1201-3799",
    "secondary_parents": [],
    "children": []
  },
  {
    "id": "F1481-1497",
    "code": "F1481-1497",
    "prefix": "F",
    "start": 1481.0,
    "end": 1497.0,
    "label": "Salvador (El Salvador)",
    "note": null,
    "primary_parent": "F1201-3799",
    "secondary_parents": [],
    "children": []
  },
  {
    "id": "F1501-1517",
    "code": "F1501-1517",
    "prefix": "F",
    "start": 1501.0,
    "end": 1517.0,
    "label": "Honduras",
    "note": null,
    "primary_parent": "F1201-3799",
    "secondary_parents": [],
    "children": []
  },
  {
    "id": "F1521-1537",
    "code": "F1521-1537",
    "prefix": "F",
    "start": 1521.0,
    "end": 1537.0,
    "label": "Nicaragua",
    "note": null,
    "primary_parent": "F1201-3799",
    "secondary_parents": [],
    "children": []
  },
  {
    "id": "F1541-1557",
    "code": "F1541-1557",
    "prefix": "F",
    "start": 1541.0,
    "end": 1557.0,
    "label": "Costa Rica",
    "note": null,
    "primary_parent": "F1201-3799",
    "secondary_parents": [],
    "children": []
  },
  {
    "id": "F1561-1577",
    "code": "F1561-1577",
    "prefix": "F",
    "start": 1561.0,
    "end": 1577.0,
    "label": "Panama",
    "note": null,
    "primary_parent": "F1201-3799",
    "secondary_parents": [],
    "children": []
  },
  {
    "id": "F1630-1640",
    "code": "F1630-1640",
    "prefix": "F",
    "start": 1630.0,
    "end": 1640.0,
    "label": "Bermudas",
    "note": null,
    "primary_parent": "F1201-3799",
    "secondary_parents": [],
    "children": []
  },
  {
    "id": "F1650-1660",
    "code": "F1650-1660",
    "prefix": "F",
    "start": 1650.0,
    "end": 1660.0,
    "label": "Bahamas",
    "note": null,
    "primary_parent": "F1201-3799",
    "secondary_parents": [],
    "children": []
  },
  {
    "id": "F1741-1991",
    "code": "F1741-1991",
    "prefix": "F",
    "start": 1741.0,
    "end": 1991.0,
    "label": "Greater Antilles",
    "note": null,
    "primary_parent": "F1201-3799",
    "secondary_parents": [],
    "children": [
      "F1751-1854.9",
      "F1861-1896",
      "F1900-1941",
      "F1951-1983",
      "F1991"
    ]
  },
  {
    "id": "F1751-1854.9",
    "code": "F1751-1854.9",
    "prefix": "F",
    "start": 1751.0,
    "end": 1854.9,
    "label": "Cuba",
    "note": null,
    "primary_parent": "F1741-1991",
    "secondary_parents": [],
    "children": [
      "F1788-1788.22"
    ]
  },
  {
    "id": "F1788-1788.22",
    "code": "F1788-1788.22",
    "prefix": "F",
    "start": 1788.0,
    "end": 1788.22,
    "label": "Communist regime",
    "note": null,
    "primary_parent": "F1751-1854.9",
    "secondary_parents": [],
    "children": []
  },
  {
    "id": "F1861-1896",
    "code": "F1861-1896",
    "prefix": "F",
    "start": 1861.0,
    "end": 1896.0,
    "label": "Jamaica",
    "note": null,
    "primary_parent": "F1741-1991",
    "secondary_parents": [],
    "children": []
  },
  {
    "id": "F1900-1941",
    "code": "F1900-1941",
    "prefix": "F",
    "start": 1900.0,
    "end": 1941.0,
    "label": "Haiti (Island).  Hispaniola",
    "note": null,
    "primary_parent": "F1741-1991",
    "secondary_parents": [],
    "children": [
      "F1912-1930",
      "F1931-1941"
    ]
  },
  {
    "id": "F1912-1930",
    "code": "F1912-1930",
    "prefix": "F",
    "start": 1912.0,
    "end": 1930.0,
    "label": "Haiti (Republic)",
    "note": null,
    "primary_parent": "F1900-1941",
    "secondary_parents": [],
    "children": []
  },
  {
    "id": "F1931-1941",
    "code": "F1931-1941",
    "prefix": "F",
    "start": 1931.0,
    "end": 1941.0,
    "label": "Dominican Republic",
    "note": null,
    "primary_parent": "F1900-1941",
    "secondary_parents": [],
    "children": []
  },
  {
    "id": "F1951-1983",
    "code": "F1951-1983",
    "prefix": "F",
    "start": 1951.0,
    "end": 1983.0,
    "label": "Puerto Rico",
    "note": null,
    "primary_parent": "F1741-1991",
    "secondary_parents": [],
    "children": []
  },
  {
    "id": "F1991",
    "code": "F1991",
    "prefix": "F",
    "start": 1991.0,
    "end": 1991.0,
    "label": "Navassa",
    "note": null,
    "primary_parent": "F1741-1991",
    "secondary_parents": [],
    "children": []
  },
  {
    "id": "F2001-2151",
    "code": "F2001-2151",
    "prefix": "F",
    "start": 2001.0,
    "end": 2151.0,
    "label": "Lesser Antilles",
    "note": null,
    "primary_parent": "F1201-3799",
    "secondary_parents": [],
    "children": [
      "F2006",
      "F2011",
      "F2016",
      "F2033-2129",
      "F2131-2133",
      "F2136",
      "F2141",
      "F2151"
    ]
  },
  {
    "id": "F2006",
    "code": "F2006",
    "prefix": "F",
    "start": 2006.0,
    "end": 2006.0,
    "label": "Leeward islands",
    "note": null,
    "primary_parent": "F2001-2151",
    "secondary_parents": [],
    "children": []
  },
  {
    "id": "F2011",
    "code": "F2011",
    "prefix": "F",
    "start": 2011.0,
    "end": 2011.0,
    "label": "Windward Islands",
    "note": null,
    "primary_parent": "F2001-2151",
    "secondary_parents": [],
    "children": []
  },
  {
    "id": "F2016",
    "code": "F2016",
    "prefix": "F",
    "start": 2016.0,
    "end": 2016.0,
    "label": "Islands along Venezuela coast",
    "note": null,
    "primary_parent": "F2001-2151",
    "secondary_parents": [],
    "children": []
  },
  {
    "id": "F2033-2129",
    "code": "F2033-2129",
    "prefix": "F",
    "start": 2033.0,
    "end": 2129.0,
    "label": "Individual islands",
    "note": null,
    "primary_parent": "F2001-2151",
    "secondary_parents": [],
    "children": []
  },
  {
    "id": "F2131-2133",
    "code": "F2131-2133",
    "prefix": "F",
    "start": 2131.0,
    "end": 2133.0,
    "label": "British West Indies",
    "note": null,
    "primary_parent": "F2001-2151",
    "secondary_parents": [],
    "children": []
  },
  {
    "id": "F2136",
    "code": "F2136",
    "prefix": "F",
    "start": 2136.0,
    "end": 2136.0,
    "label": "Virgin Islands of the United States",
    "note": null,
    "primary_parent": "F2001-2151",
    "secondary_parents": [],
    "children": []
  },
  {
    "id": "F2141",
    "code": "F2141",
    "prefix": "F",
    "start": 2141.0,
    "end": 2141.0,
    "label": "Netherlands West Indies.  Dutch West Indies",
    "note": null,
    "primary_parent": "F2001-2151",
    "secondary_parents": [],
    "children": []
  },
  {
    "id": "F2151",
    "code": "F2151",
    "prefix": "F",
    "start": 2151.0,
    "end": 2151.0,
    "label": "French West Indies",
    "note": null,
    "primary_parent": "F2001-2151",
    "secondary_parents": [],
    "children": []
  },
  {
    "id": "F2155-2191",
    "code": "F2155-2191",
    "prefix": "F",
    "start": 2155.0,
    "end": 2191.0,
    "label": "Caribbean area.  Caribbean Sea",
    "note": null,
    "primary_parent": "F1201-3799",
    "secondary_parents": [],
    "children": []
  },
  {
    "id": "F2201-3799",
    "code": "F2201-3799",
    "prefix": "F",
    "start": 2201.0,
    "end": 3799.0,
    "label": "South America",
    "note": null,
    "primary_parent": "F1201-3799",
    "secondary_parents": [],
    "children": [
      "F2201-2239",
      "F2251-2299",
      "F2301-2349",
      "F2351",
      "F2361-2391",
      "F2401-2431",
      "F2441-2471",
      "F2501-2659",
      "F2661-2699",
      "F2701-2799",
      "F2801-3021",
      "F3031-3031.5",
      "F3051-3285",
      "F3301-3359",
      "F3401-3619",
      "F3701-3799"
    ]
  },
  {
    "id": "F2201-2239",
    "code": "F2201-2239",
    "prefix": "F",
    "start": 2201.0,
    "end": 2239.0,
    "label": "General",
    "note": null,
    "primary_parent": "F2201-3799",
    "secondary_parents": [],
    "children": []
  },
  {
    "id": "F2251-2299",
    "code": "F2251-2299",
    "prefix": "F",
    "start": 2251.0,
    "end": 2299.0,
    "label": "Colombia",
    "note": null,
    "primary_parent": "F2201-3799",
    "secondary_parents": [],
    "children": []
  },
  {
    "id": "F2301-2349",
    "code": "F2301-2349",
    "prefix": "F",
    "start": 2301.0,
    "end": 2349.0,
    "label": "Venezuela",
    "note": null,
    "primary_parent": "F2201-3799",
    "secondary_parents": [],
    "children": []
  },
  {
    "id": "F2351",
    "code": "F2351",
    "prefix": "F",
    "start": 2351.0,
    "end": 2351.0,
    "label": "Guiana",
    "note": null,
    "primary_parent": "F2201-3799",
    "secondary_parents": [],
    "children": []
  },
  {
    "id": "F2361-2391",
    "code": "F2361-2391",
    "prefix": "F",
    "start": 2361.0,
    "end": 2391.0,
    "label": "Guyana.  British Guiana",
    "note": null,
    "primary_parent": "F2201-3799",
    "secondary_parents": [],
    "children": []
  },
  {
    "id": "F2401-2431",
    "code": "F2401-2431",
    "prefix": "F",
    "start": 2401.0,
    "end": 2431.0,
    "label": "Surinam",
    "note": null,
    "primary_parent": "F2201-3799",
    "secondary_parents": [],
    "children": []
  },
  {
    "id": "F2441-2471",
    "code": "F2441-2471",
    "prefix": "F",
    "start": 2441.0,
    "end": 2471.0,
    "label": "French Guiana",
    "note": null,
    "primary_parent": "F2201-3799",
    "secondary_parents": [],
    "children": []
  },
  {
    "id": "F2501-2659",
    "code": "F2501-2659",
    "prefix": "F",
    "start": 2501.0,
    "end": 2659.0,
    "label": "Brazil",
    "note": null,
    "primary_parent": "F2201-3799",
    "secondary_parents": [],
    "children": []
  },
  {
    "id": "F2661-2699",
    "code": "F2661-2699",
    "prefix": "F",
    "start": 2661.0,
    "end": 2699.0,
    "label": "Paraguay",
    "note": null,
    "primary_parent": "F2201-3799",
    "secondary_parents": [],
    "children": []
  },
  {
    "id": "F2701-2799",
    "code": "F2701-2799",
    "prefix": "F",
    "start": 2701.0,
    "end": 2799.0,
    "label": "Uruguay",
    "note": null,
    "primary_parent": "F2201-3799",
    "secondary_parents": [],
    "children": []
  },
  {
    "id": "F2801-3021",
    "code": "F2801-3021",
    "prefix": "F",
    "start": 2801.0,
    "end": 3021.0,
    "label": "Argentina",
    "note": null,
    "primary_parent": "F2201-3799",
    "secondary_parents": [],
    "children": []
  },
  {
    "id": "F3031-3031.5",
    "code": "F3031-3031.5",
    "prefix": "F",
    "start": 3031.0,
    "end": 3031.5,
    "label": "Falkland Islands",
    "note": null,
    "primary_parent": "F2201-3799",
    "secondary_parents": [],
    "children": []
  },
  {
    "id": "F3051-3285",
    "code": "F3051-3285",
    "prefix": "F",
    "start": 3051.0,
    "end": 3285.0,
    "label": "Chile",
    "note": null,
    "primary_parent": "F2201-3799",
    "secondary_parents": [],
    "children": []
  },
  {
    "id": "F3301-3359",
    "code": "F3301-3359",
    "prefix": "F",
    "start": 3301.0,
    "end": 3359.0,
    "label": "Bolivia",
    "note": null,
    "primary_parent": "F2201-3799",
    "secondary_parents": [],
    "children": []
  },
  {
    "id": "F3401-3619",
    "code": "F3401-3619",
    "prefix": "F",
    "start": 3401.0,
    "end": 3619.0,
    "label": "Peru",
    "note": null,
    "primary_parent": "F2201-3799",
    "secondary_parents": [],
    "children": []
  },
  {
    "id": "F3701-3799",
    "code": "F3701-3799",
    "prefix": "F",
    "start": 3701.0,
    "end": 3799.0,
    "label": "Ecuador",
    "note": null,
    "primary_parent": "F2201-3799",
    "secondary_parents": [],
    "children": []
  }
]